INSTALL
LICENSE
MANIFEST.in
README.rst
setup.py
mtg_deck_editor.egg-info/PKG-INFO
mtg_deck_editor.egg-info/SOURCES.txt
mtg_deck_editor.egg-info/dependency_links.txt
mtg_deck_editor.egg-info/entry_points.txt
mtg_deck_editor.egg-info/requires.txt
mtg_deck_editor.egg-info/top_level.txt
mtg_deck_editor.egg-info/zip-safe
mtgdeckeditor/Interface.GtkBuilder
mtgdeckeditor/__init__.py
mtgdeckeditor/__main__.py