Metadata-Version: 1.1
Name: mtg-deck-editor
Version: 1.0.2
Summary: A GUI deck editor for the card game Magic: The Gathering.
Home-page: https://github.com/buckket/mtg-deck-editor
Author: buckket
Author-email: buckket@cock.li
License: GPLv3
Keywords: mtg,deck editor,card game
Platform: any
Classifier: Programming Language :: Python
Classifier: Operating System :: OS Independent
Classifier: Development Status :: 5 - Production/Stable
Classifier: License :: OSI Approved :: GNU General Public License v3 or later (GPLv3+)
Classifier: Intended Audience :: End Users/Desktop
Classifier: Topic :: Games/Entertainment
